backup_to_harddrive/__init__.py
backup_to_harddrive/backup_from_config.py
backup_to_harddrive/backup_status.py
backup_to_harddrive/config.py
backup_to_harddrive/main.py
backup_to_harddrive/rsync_installation_check.py
backup_to_harddrive-0.0.5.dist-info/entry_points.txt
backup_to_harddrive-0.0.5.dist-info/LICENSE
backup_to_harddrive-0.0.5.dist-info/WHEEL
backup_to_harddrive-0.0.5.dist-info/METADATA
backup_to_harddrive-0.0.5.dist-info/RECORD
