Metadata-Version: 2.1
Name: backup-to-harddrive
Version: 0.0.5
Summary: Backup home files to Harddrive on Linux
Author: Maxime Haselbauer
Author-email: maxime.haselbauer@googlemail.com
Classifier: Programming Language :: Python :: 2
Classifier: Programming Language :: Python :: 2.7
Classifier: Programming Language :: Python :: 3
Classifier: Programming Language :: Python :: 3.4
Classifier: Programming Language :: Python :: 3.5
Classifier: Programming Language :: Python :: 3.6
Classifier: Programming Language :: Python :: 3.7
Classifier: Programming Language :: Python :: 3.8
Classifier: Programming Language :: Python :: 3.9
Classifier: Programming Language :: Python :: 3.10
Requires-Dist: PyYAML (==6.0.2)
Requires-Dist: platformdirs (>=3.0.0,<4.0.0)
